sqlflow/__init__.py
sqlflow/logging.py
sqlflow/main.py
sqlflow/project.py
sqlflow/cli/__init__.py
sqlflow/cli/connect.py
sqlflow/cli/main.py
sqlflow/cli/pipeline.py
sqlflow/cli/test_variable_handler.py
sqlflow/cli/utils.py
sqlflow/cli/validation_cache.py
sqlflow/cli/validation_helpers.py
sqlflow/cli/variable_handler.py
sqlflow/cli/commands/__init__.py
sqlflow/cli/commands/udf.py
sqlflow/connectors/__init__.py
sqlflow/connectors/base.py
sqlflow/connectors/connector_engine.py
sqlflow/connectors/csv_connector.py
sqlflow/connectors/csv_export_connector.py
sqlflow/connectors/data_chunk.py
sqlflow/connectors/google_sheets_connector.py
sqlflow/connectors/parquet_connector.py
sqlflow/connectors/postgres_connector.py
sqlflow/connectors/postgres_export_connector.py
sqlflow/connectors/postgres_placeholder.py
sqlflow/connectors/registry.py
sqlflow/connectors/rest_connector.py
sqlflow/connectors/s3_connector.py
sqlflow/core/__init__.py
sqlflow/core/dependencies.py
sqlflow/core/errors.py
sqlflow/core/evaluator.py
sqlflow/core/planner.py
sqlflow/core/protocols.py
sqlflow/core/sql_generator.py
sqlflow/core/variables.py
sqlflow/core/debug/timer.py
sqlflow/core/engines/__init__.py
sqlflow/core/engines/base.py
sqlflow/core/engines/duckdb/__init__.py
sqlflow/core/engines/duckdb/constants.py
sqlflow/core/engines/duckdb/engine.py
sqlflow/core/engines/duckdb/exceptions.py
sqlflow/core/engines/duckdb/transaction_manager.py
sqlflow/core/engines/duckdb/data/__init__.py
sqlflow/core/engines/duckdb/data/handlers.py
sqlflow/core/engines/duckdb/data/registration.py
sqlflow/core/engines/duckdb/load/__init__.py
sqlflow/core/engines/duckdb/load/handlers.py
sqlflow/core/engines/duckdb/load/sql_generators.py
sqlflow/core/engines/duckdb/udf/__init__.py
sqlflow/core/engines/duckdb/udf/dependencies.py
sqlflow/core/engines/duckdb/udf/handlers.py
sqlflow/core/engines/duckdb/udf/performance.py
sqlflow/core/engines/duckdb/udf/query_processor.py
sqlflow/core/engines/duckdb/udf/registration.py
sqlflow_core-0.1.7.dist-info/licenses/LICENSE
sqlflow_core-0.1.7.dist-info/METADATA
sqlflow_core-0.1.7.dist-info/WHEEL
sqlflow_core-0.1.7.dist-info/entry_points.txt
sqlflow_core-0.1.7.dist-info/top_level.txt
sqlflow_core-0.1.7.dist-info/RECORD
