Metadata-Version: 2.4
Name: sqlflow-core
Version: 0.1.7
Summary: SQLFlow is a SQL-native engine for defining, orchestrating, and managing data workflows—empowering analysts and engineers to build robust, production-grade pipelines using only SQL.
Author-email: Chanh Le <giaosudau@gmail.com>
License:                                  Apache License
Project-URL: Homepage, https://github.com/sqlflow/sqlflow
Project-URL: Documentation, https://github.com/sqlflow/sqlflow#readme
Project-URL: Source, https://github.com/sqlflow/sqlflow
Project-URL: Tracker, https://github.com/sqlflow/sqlflow/issues
Keywords: sql,data-pipeline,etl,workflow,duckdb,analytics,data-engineering
Classifier: Development Status :: 3 - Alpha
Classifier: Intended Audience :: Developers
Classifier: Intended Audience :: Information Technology
Classifier: Intended Audience :: Science/Research
Classifier: License :: OSI Approved :: Apache Software License
Classifier: Programming Language :: Python :: 3
Classifier: Programming Language :: Python :: 3.10
Classifier: Programming Language :: Python :: 3.11
Classifier: Operating System :: OS Independent
Classifier: Topic :: Database
Classifier: Topic :: Software Development :: Libraries :: Python Modules
Classifier: Topic :: Scientific/Engineering :: Information Analysis
Requires-Python: >=3.10
License-File: LICENSE
Requires-Dist: duckdb>=1.2.0
Requires-Dist: pandas>=2.0.0
Requires-Dist: click>=8.0.0
Requires-Dist: networkx>=3.0
Requires-Dist: typer==0.9.0
Requires-Dist: rich>=13.0.0
Requires-Dist: requests>=2.28.0
Requires-Dist: pyyaml>=6.0
Requires-Dist: typing-extensions>=4.0.0
Requires-Dist: pyarrow>=10.0.0
Provides-Extra: postgres
Requires-Dist: psycopg2-binary>=2.9.0; platform_machine != "aarch64" and extra == "postgres"
Requires-Dist: psycopg2>=2.9.0; platform_machine == "aarch64" and extra == "postgres"
Provides-Extra: cloud
Requires-Dist: boto3>=1.26.0; extra == "cloud"
Requires-Dist: botocore>=1.29.0; extra == "cloud"
Requires-Dist: google-api-python-client>=2.0.0; extra == "cloud"
Requires-Dist: google-auth>=2.0.0; extra == "cloud"
Requires-Dist: google-auth-oauthlib>=1.0.0; extra == "cloud"
Requires-Dist: google-cloud-storage>=2.0.0; extra == "cloud"
Provides-Extra: all
Requires-Dist: psycopg2-binary>=2.9.0; platform_machine != "aarch64" and extra == "all"
Requires-Dist: psycopg2>=2.9.0; platform_machine == "aarch64" and extra == "all"
Requires-Dist: boto3>=1.26.0; extra == "all"
Requires-Dist: botocore>=1.29.0; extra == "all"
Requires-Dist: google-api-python-client>=2.0.0; extra == "all"
Requires-Dist: google-auth>=2.0.0; extra == "all"
Requires-Dist: google-auth-oauthlib>=1.0.0; extra == "all"
Requires-Dist: google-cloud-storage>=2.0.0; extra == "all"
Provides-Extra: dev
Requires-Dist: pytest>=7.0.0; extra == "dev"
Requires-Dist: pytest-cov>=4.1.0; extra == "dev"
Requires-Dist: pytest-xdist>=3.0.0; extra == "dev"
Requires-Dist: black>=22.1.0; extra == "dev"
Requires-Dist: isort>=5.10.1; extra == "dev"
Requires-Dist: flake8>=4.0.1; extra == "dev"
Requires-Dist: flake8-pyproject>=1.2.3; extra == "dev"
Requires-Dist: autoflake>=2.2.0; extra == "dev"
Requires-Dist: pre-commit>=3.0.0; extra == "dev"
Requires-Dist: mypy>=1.0.0; extra == "dev"
Provides-Extra: test
Requires-Dist: pytest>=7.0.0; extra == "test"
Requires-Dist: pytest-cov>=4.1.0; extra == "test"
Requires-Dist: mock>=5.0.0; extra == "test"
Provides-Extra: docs
Requires-Dist: sphinx>=4.0.0; extra == "docs"
Requires-Dist: sphinx-rtd-theme>=1.0.0; extra == "docs"
Requires-Dist: myst-parser>=1.0.0; extra == "docs"
Dynamic: license-file
